direct_debit/__init__.py
direct_debit/classes.py
direct_debit/client.py
direct_debit-0.0.0.dist-info/LICENCE
direct_debit-0.0.0.dist-info/METADATA
direct_debit-0.0.0.dist-info/WHEEL
direct_debit-0.0.0.dist-info/top_level.txt
direct_debit-0.0.0.dist-info/RECORD
