Metadata-Version: 2.1
Name: direct-debit
Version: 0.0.0
Summary: A wrapper around Direct Debit's debit order collection API.
Home-page: https://directdebit.co.za
Author: direct debit
Author-email: arie@directdebit.co.za
License: UNKNOWN
Project-URL: Source Code, https://github.com/Direct-Debit/direct-debit-python-client
Platform: UNKNOWN
Classifier: Programming Language :: Python :: 3
Classifier: License :: OSI Approved :: MIT License
Classifier: Operating System :: OS Independent
Requires-Python: >=3.6
